./.gitignore
./LICENSE
./PKG-INFO
./README.md
./mk2html.py
./mk2pdf.py
./pyproject.toml
mk2html-1.4.0.dist-info/METADATA
mk2html-1.4.0.dist-info/WHEEL
mk2html-1.4.0.dist-info/entry_points.txt
mk2html-1.4.0.dist-info/licenses/LICENSE
mk2html-1.4.0.dist-info/RECORD
