Metadata-Version: 2.4
Name: mk2html
Version: 1.4.0
Summary: Convert Markdown to beautiful, interactive HTML and PDF with TOC, dark/light mode, Mermaid diagrams, and syntax highlighting
Project-URL: Homepage, https://github.com/km1790/mk2html
Project-URL: Documentation, https://github.com/km1790/mk2html#readme
Project-URL: Repository, https://github.com/km1790/mk2html
Project-URL: Issues, https://github.com/km1790/mk2html/issues
Author: Kinshuk
License: MIT
License-File: LICENSE
Keywords: converter,dark-mode,html,markdown,mermaid,pdf,syntax-highlighting,table-of-contents,toc
Classifier: Development Status :: 4 - Beta
Classifier: Environment :: Console
Classifier: Intended Audience :: Developers
Classifier: License :: OSI Approved :: MIT License
Classifier: Operating System :: OS Independent
Classifier: Programming Language :: Python :: 3
Classifier: Programming Language :: Python :: 3.9
Classifier: Programming Language :: Python :: 3.10
Classifier: Programming Language :: Python :: 3.11
Classifier: Programming Language :: Python :: 3.12
Classifier: Programming Language :: Python :: 3.13
Classifier: Topic :: Documentation
Classifier: Topic :: Text Processing :: Markup :: HTML
Classifier: Topic :: Text Processing :: Markup :: Markdown
Requires-Python: >=3.9
Requires-Dist: markdown>=3.4.0
Requires-Dist: pygments>=2.15.0
Provides-Extra: all
Requires-Dist: playwright>=1.40.0; extra == 'all'
Requires-Dist: pytest-cov>=4.0.0; extra == 'all'
Requires-Dist: pytest>=7.0.0; extra == 'all'
Provides-Extra: dev
Requires-Dist: pytest-cov>=4.0.0; extra == 'dev'
Requires-Dist: pytest>=7.0.0; extra == 'dev'
Provides-Extra: pdf
Requires-Dist: playwright>=1.40.0; extra == 'pdf'
